matrice_analytics/__init__.py
matrice_analytics/py.typed
matrice_analytics/boundary_drawing_internal/README.md
matrice_analytics/boundary_drawing_internal/__init__.py
matrice_analytics/boundary_drawing_internal/boundary_drawing_internal.py
matrice_analytics/boundary_drawing_internal/boundary_drawing_tool.py
matrice_analytics/boundary_drawing_internal/boundary_tool_template.html
matrice_analytics/boundary_drawing_internal/example_usage.py
matrice_analytics/boundary_drawing_internal/data/.gitignore
matrice_analytics/boundary_drawing_internal/usage/README.md
matrice_analytics/boundary_drawing_internal/usage/boundary_drawer_launcher.py
matrice_analytics/boundary_drawing_internal/usage/simple_boundary_launcher.py
matrice_analytics/post_processing/README.md
matrice_analytics/post_processing/__init__.py
matrice_analytics/post_processing/config.py
matrice_analytics/post_processing/post_processor.py
matrice_analytics/post_processing/advanced_tracker/README.md
matrice_analytics/post_processing/advanced_tracker/__init__.py
matrice_analytics/post_processing/advanced_tracker/base.py
matrice_analytics/post_processing/advanced_tracker/config.py
matrice_analytics/post_processing/advanced_tracker/kalman_filter.py
matrice_analytics/post_processing/advanced_tracker/matching.py
matrice_analytics/post_processing/advanced_tracker/strack.py
matrice_analytics/post_processing/advanced_tracker/tracker.py
matrice_analytics/post_processing/core/__init__.py
matrice_analytics/post_processing/core/base.py
matrice_analytics/post_processing/core/config.py
matrice_analytics/post_processing/core/config_utils.py
matrice_analytics/post_processing/face_reg/__init__.py
matrice_analytics/post_processing/face_reg/compare_similarity.py
matrice_analytics/post_processing/face_reg/embedding_manager.py
matrice_analytics/post_processing/face_reg/face_recognition.py
matrice_analytics/post_processing/face_reg/face_recognition_client.py
matrice_analytics/post_processing/face_reg/people_activity_logging.py
matrice_analytics-0.1.578.dist-info/licenses/LICENSE.txt
matrice_analytics-0.1.578.dist-info/METADATA
matrice_analytics-0.1.578.dist-info/WHEEL
matrice_analytics-0.1.578.dist-info/top_level.txt
matrice_analytics-0.1.578.dist-info/RECORD
